Metadata-Version: 2.1
Name: jamdict_data_fix
Version: 1.5.1a2
Summary: Precompiled database for jamdict library for manipulating Jim Breen's JMdict, KanjiDic2, KRADFILE and JMnedict. Compiled date: 17 Apr 2021.
Home-page: https://github.com/neocl/jamdict_data
Author: Le Tuan Anh
Author-email: tuananh.ke@gmail.com
License: MIT License
Keywords: nlp
Platform: any
Classifier: Programming Language :: Python
Classifier: Development Status :: 2 - Pre-Alpha
Classifier: Natural Language :: Japanese
Classifier: Environment :: Plugins
Classifier: Intended Audience :: Developers
Classifier: License :: OSI Approved :: MIT License
Classifier: Operating System :: OS Independent
Classifier: Topic :: Database
Classifier: Topic :: Text Processing :: Linguistic
Classifier: Topic :: Software Development :: Libraries :: Python Modules
License-File: LICENSE
